<annotation>
  <folder>IMG</folder>
  <filename>IMG_20210218_105202_BURST019.resized.jpg</filename>
  <source>
    <database>Unknown</database>
    <annotation>Unknown</annotation>
    <image>Unknown</image>
  </source>
  <size>
    <width>2000</width>
    <height>1500</height>
    <depth></depth>
  </size>
  <segmented>0</segmented>
  <object>
    <name>nut</name>
    <occluded>0</occluded>
    <bndbox>
      <xmin>1432.89</xmin>
      <ymin>752.35</ymin>
      <xmax>1506.71</xmax>
      <ymax>821.11</ymax>
    </bndbox>
  </object>
  <object>
    <name>bolt</name>
    <occluded>0</occluded>
    <bndbox>
      <xmin>433.1</xmin>
      <ymin>581.72</ymin>
      <xmax>594.87</xmax>
      <ymax>1050.6</ymax>
    </bndbox>
  </object>
  <object>
    <name>bolt</name>
    <occluded>0</occluded>
    <bndbox>
      <xmin>624.46</xmin>
      <ymin>780.32</ymin>
      <xmax>775.71</xmax>
      <ymax>937.49</ymax>
    </bndbox>
  </object>
  <object>
    <name>bolt</name>
    <occluded>0</occluded>
    <bndbox>
      <xmin>533.71</xmin>
      <ymin>973.0</ymin>
      <xmax>777.69</xmax>
      <ymax>1088.08</ymax>
    </bndbox>
  </object>
  <object>
    <name>bolt</name>
    <occluded>0</occluded>
    <bndbox>
      <xmin>657.34</xmin>
      <ymin>1190.67</ymin>
      <xmax>724.42</xmax>
      <ymax>1305.1</ymax>
    </bndbox>
  </object>
  <object>
    <name>bolt</name>
    <occluded>0</occluded>
    <bndbox>
      <xmin>773.74</xmin>
      <ymin>1269.6</ymin>
      <xmax>880.9</xmax>
      <ymax>1339.29</ymax>
    </bndbox>
  </object>
  <object>
    <name>bolt</name>
    <occluded>0</occluded>
    <bndbox>
      <xmin>917.96</xmin>
      <ymin>1120.42</ymin>
      <xmax>970.48</xmax>
      <ymax>1189.72</ymax>
    </bndbox>
  </object>
  <object>
    <name>bolt</name>
    <occluded>0</occluded>
    <bndbox>
      <xmin>965.53</xmin>
      <ymin>1145.92</ymin>
      <xmax>1032.13</xmax>
      <ymax>1269.64</ymax>
    </bndbox>
  </object>
  <object>
    <name>bolt</name>
    <occluded>0</occluded>
    <bndbox>
      <xmin>984.18</xmin>
      <ymin>1192.77</ymin>
      <xmax>1038.6</xmax>
      <ymax>1286.0</ymax>
    </bndbox>
  </object>
  <object>
    <name>bolt</name>
    <occluded>0</occluded>
    <bndbox>
      <xmin>1031.75</xmin>
      <ymin>1155.81</ymin>
      <xmax>1069.8</xmax>
      <ymax>1265.83</ymax>
    </bndbox>
  </object>
  <object>
    <name>bolt</name>
    <occluded>0</occluded>
    <bndbox>
      <xmin>1058.39</xmin>
      <ymin>1095.72</ymin>
      <xmax>1121.9</xmax>
      <ymax>1200.0</ymax>
    </bndbox>
  </object>
  <object>
    <name>bolt</name>
    <occluded>0</occluded>
    <bndbox>
      <xmin>1110.14</xmin>
      <ymin>1203.8</ymin>
      <xmax>1236.87</xmax>
      <ymax>1287.91</ymax>
    </bndbox>
  </object>
  <object>
    <name>bolt</name>
    <occluded>0</occluded>
    <bndbox>
      <xmin>554.75</xmin>
      <ymin>408.11</ymin>
      <xmax>651.42</xmax>
      <ymax>537.0</ymax>
    </bndbox>
  </object>
  <object>
    <name>nut</name>
    <occluded>0</occluded>
    <bndbox>
      <xmin>774.39</xmin>
      <ymin>1016.65</ymin>
      <xmax>811.61</xmax>
      <ymax>1060.48</ymax>
    </bndbox>
  </object>
  <object>
    <name>nut</name>
    <occluded>0</occluded>
    <bndbox>
      <xmin>897.95</xmin>
      <ymin>601.65</ymin>
      <xmax>934.74</xmax>
      <ymax>645.77</ymax>
    </bndbox>
  </object>
  <object>
    <name>nut</name>
    <occluded>0</occluded>
    <bndbox>
      <xmin>819.9</xmin>
      <ymin>597.88</ymin>
      <xmax>866.24</xmax>
      <ymax>631.81</ymax>
    </bndbox>
  </object>
  <object>
    <name>nut</name>
    <occluded>0</occluded>
    <bndbox>
      <xmin>827.55</xmin>
      <ymin>631.46</ymin>
      <xmax>874.49</xmax>
      <ymax>674.31</ymax>
    </bndbox>
  </object>
  <object>
    <name>nut</name>
    <occluded>0</occluded>
    <bndbox>
      <xmin>787.59</xmin>
      <ymin>697.11</ymin>
      <xmax>833.26</xmax>
      <ymax>742.49</ymax>
    </bndbox>
  </object>
  <object>
    <name>nut</name>
    <occluded>0</occluded>
    <bndbox>
      <xmin>760.63</xmin>
      <ymin>633.68</ymin>
      <xmax>802.81</xmax>
      <ymax>681.6</ymax>
    </bndbox>
  </object>
  <object>
    <name>nut</name>
    <occluded>0</occluded>
    <bndbox>
      <xmin>718.77</xmin>
      <ymin>671.11</ymin>
      <xmax>748.9</xmax>
      <ymax>712.7</ymax>
    </bndbox>
  </object>
  <object>
    <name>bolt</name>
    <occluded>0</occluded>
    <bndbox>
      <xmin>855.74</xmin>
      <ymin>494.24</ymin>
      <xmax>978.51</xmax>
      <ymax>585.89</ymax>
    </bndbox>
  </object>
  <object>
    <name>bolt</name>
    <occluded>0</occluded>
    <bndbox>
      <xmin>746.33</xmin>
      <ymin>433.0</ymin>
      <xmax>876.71</xmax>
      <ymax>489.8</ymax>
    </bndbox>
  </object>
  <object>
    <name>bolt</name>
    <occluded>0</occluded>
    <bndbox>
      <xmin>802.18</xmin>
      <ymin>368.3</ymin>
      <xmax>931.57</xmax>
      <ymax>421.29</ymax>
    </bndbox>
  </object>
  <object>
    <name>bolt</name>
    <occluded>0</occluded>
    <bndbox>
      <xmin>940.74</xmin>
      <ymin>353.71</ymin>
      <xmax>1061.91</xmax>
      <ymax>430.81</ymax>
    </bndbox>
  </object>
  <object>
    <name>bolt</name>
    <occluded>0</occluded>
    <bndbox>
      <xmin>920.76</xmin>
      <ymin>360.4</ymin>
      <xmax>1037.81</xmax>
      <ymax>449.84</ymax>
    </bndbox>
  </object>
  <object>
    <name>bolt</name>
    <occluded>0</occluded>
    <bndbox>
      <xmin>1135.46</xmin>
      <ymin>353.4</ymin>
      <xmax>1261.39</xmax>
      <ymax>429.86</ymax>
    </bndbox>
  </object>
  <object>
    <name>bolt</name>
    <occluded>0</occluded>
    <bndbox>
      <xmin>1248.04</xmin>
      <ymin>370.84</ymin>
      <xmax>1304.84</xmax>
      <ymax>499.94</ymax>
    </bndbox>
  </object>
  <object>
    <name>bolt</name>
    <occluded>0</occluded>
    <bndbox>
      <xmin>1082.85</xmin>
      <ymin>480.92</ymin>
      <xmax>1210.02</xmax>
      <ymax>536.42</ymax>
    </bndbox>
  </object>
  <object>
    <name>bolt</name>
    <occluded>0</occluded>
    <bndbox>
      <xmin>993.95</xmin>
      <ymin>645.08</ymin>
      <xmax>1170.95</xmax>
      <ymax>707.55</ymax>
    </bndbox>
  </object>
  <object>
    <name>bolt</name>
    <occluded>0</occluded>
    <bndbox>
      <xmin>921.61</xmin>
      <ymin>710.29</ymin>
      <xmax>1096.97</xmax>
      <ymax>779.34</ymax>
    </bndbox>
  </object>
  <object>
    <name>bolt</name>
    <occluded>0</occluded>
    <bndbox>
      <xmin>796.6</xmin>
      <ymin>763.39</ymin>
      <xmax>897.49</xmax>
      <ymax>938.27</ymax>
    </bndbox>
  </object>
  <object>
    <name>bolt</name>
    <occluded>0</occluded>
    <bndbox>
      <xmin>876.07</xmin>
      <ymin>804.55</ymin>
      <xmax>1052.03</xmax>
      <ymax>905.39</ymax>
    </bndbox>
  </object>
  <object>
    <name>bolt</name>
    <occluded>0</occluded>
    <bndbox>
      <xmin>1137.27</xmin>
      <ymin>452.96</ymin>
      <xmax>1500.28</xmax>
      <ymax>772.56</ymax>
    </bndbox>
  </object>
  <object>
    <name>bolt</name>
    <occluded>0</occluded>
    <bndbox>
      <xmin>1257.7</xmin>
      <ymin>692.64</ymin>
      <xmax>1375.98</xmax>
      <ymax>916.86</ymax>
    </bndbox>
  </object>
  <object>
    <name>bolt</name>
    <occluded>0</occluded>
    <bndbox>
      <xmin>1062.33</xmin>
      <ymin>857.55</ymin>
      <xmax>1259.27</xmax>
      <ymax>1043.71</ymax>
    </bndbox>
  </object>
  <object>
    <name>bolt</name>
    <occluded>0</occluded>
    <bndbox>
      <xmin>1067.08</xmin>
      <ymin>1029.76</ymin>
      <xmax>1106.09</xmax>
      <ymax>1068.45</ymax>
    </bndbox>
  </object>
  <object>
    <name>bolt</name>
    <occluded>0</occluded>
    <bndbox>
      <xmin>1148.96</xmin>
      <ymin>1188.92</ymin>
      <xmax>1283.68</xmax>
      <ymax>1228.3</ymax>
    </bndbox>
  </object>
  <object>
    <name>nut</name>
    <occluded>0</occluded>
    <bndbox>
      <xmin>973.05</xmin>
      <ymin>571.98</ymin>
      <xmax>1012.87</xmax>
      <ymax>614.02</ymax>
    </bndbox>
  </object>
  <object>
    <name>nut</name>
    <occluded>0</occluded>
    <bndbox>
      <xmin>1011.11</xmin>
      <ymin>551.09</ymin>
      <xmax>1042.22</xmax>
      <ymax>594.86</ymax>
    </bndbox>
  </object>
  <object>
    <name>nut</name>
    <occluded>0</occluded>
    <bndbox>
      <xmin>1061.75</xmin>
      <ymin>594.39</ymin>
      <xmax>1107.26</xmax>
      <ymax>629.71</ymax>
    </bndbox>
  </object>
  <object>
    <name>nut</name>
    <occluded>0</occluded>
    <bndbox>
      <xmin>1435.4</xmin>
      <ymin>633.44</ymin>
      <xmax>1504.56</xmax>
      <ymax>699.7</ymax>
    </bndbox>
  </object>
  <object>
    <name>nut</name>
    <occluded>0</occluded>
    <bndbox>
      <xmin>1547.15</xmin>
      <ymin>718.68</ymin>
      <xmax>1618.82</xmax>
      <ymax>788.52</ymax>
    </bndbox>
  </object>
  <object>
    <name>nut</name>
    <occluded>0</occluded>
    <bndbox>
      <xmin>1620.93</xmin>
      <ymin>835.08</ymin>
      <xmax>1691.52</xmax>
      <ymax>880.21</ymax>
    </bndbox>
  </object>
  <object>
    <name>nut</name>
    <occluded>0</occluded>
    <bndbox>
      <xmin>1579.38</xmin>
      <ymin>798.91</ymin>
      <xmax>1641.74</xmax>
      <ymax>870.18</ymax>
    </bndbox>
  </object>
  <object>
    <name>nut</name>
    <occluded>0</occluded>
    <bndbox>
      <xmin>1591.96</xmin>
      <ymin>951.48</ymin>
      <xmax>1651.05</xmax>
      <ymax>1009.87</ymax>
    </bndbox>
  </object>
  <object>
    <name>nut</name>
    <occluded>0</occluded>
    <bndbox>
      <xmin>1475.91</xmin>
      <ymin>947.54</ymin>
      <xmax>1544.32</xmax>
      <ymax>1005.57</ymax>
    </bndbox>
  </object>
  <object>
    <name>nut</name>
    <occluded>0</occluded>
    <bndbox>
      <xmin>1410.72</xmin>
      <ymin>959.01</ymin>
      <xmax>1458.72</xmax>
      <ymax>1019.89</ymax>
    </bndbox>
  </object>
  <object>
    <name>nut</name>
    <occluded>0</occluded>
    <bndbox>
      <xmin>1427.88</xmin>
      <ymin>1017.03</ymin>
      <xmax>1490.59</xmax>
      <ymax>1075.41</ymax>
    </bndbox>
  </object>
  <object>
    <name>nut</name>
    <occluded>0</occluded>
    <bndbox>
      <xmin>1487.33</xmin>
      <ymin>1024.91</ymin>
      <xmax>1551.12</xmax>
      <ymax>1073.62</ymax>
    </bndbox>
  </object>
  <object>
    <name>nut</name>
    <occluded>0</occluded>
    <bndbox>
      <xmin>1408.18</xmin>
      <ymin>1054.28</ymin>
      <xmax>1469.46</xmax>
      <ymax>1106.57</ymax>
    </bndbox>
  </object>
  <object>
    <name>nut</name>
    <occluded>0</occluded>
    <bndbox>
      <xmin>913.71</xmin>
      <ymin>1071.58</ymin>
      <xmax>968.11</xmax>
      <ymax>1101.75</ymax>
    </bndbox>
  </object>
  <object>
    <name>nut</name>
    <occluded>0</occluded>
    <bndbox>
      <xmin>845.22</xmin>
      <ymin>1095.8</ymin>
      <xmax>872.09</xmax>
      <ymax>1144.26</ymax>
    </bndbox>
  </object>
  <object>
    <name>nut</name>
    <occluded>0</occluded>
    <bndbox>
      <xmin>816.57</xmin>
      <ymin>1031.72</ymin>
      <xmax>868.35</xmax>
      <ymax>1071.14</ymax>
    </bndbox>
  </object>
</annotation>
